<?xml version="1.0" encoding="UTF-8"?>

<recipeml version="0.5">
  <recipe>
    <head>
      <title>Banana Split Cake #2</title>
      <categories>
        <cat>Cake</cat></categories>
      <yield>15</yield></head>
    <ingredients>
      <ing>
        <amt>
          <qty>2</qty>
          <unit>cups</unit></amt>
        <item>Graham cracker crumbs</item></ing>
      <ing>
        <amt>
          <qty>5</qty>
          <unit>tablespoons</unit></amt>
        <item>Melted butter</item></ing>
      <ing>
        <amt>
          <qty>1/2</qty>
          <unit>pounds</unit></amt>
        <item>Soft butter</item></ing>
      <ing>
        <amt>
          <qty>2</qty>
          <unit>cups</unit></amt>
        <item>Powdered sugar</item></ing>
      <ing>
        <amt>
          <qty>1</qty>
          <unit>teaspoon</unit></amt>
        <item>Vanilla</item></ing>
      <ing>
        <amt>
          <qty>2</qty>
          <unit/></amt>
        <item>Eggs (up to)</item></ing>
      <ing>
        <amt>
          <qty>5</qty>
          <unit>medium</unit></amt>
        <item>Bananas</item></ing>
      <ing>
        <amt>
          <qty>1</qty>
          <unit>can</unit></amt>
        <item>(large) crushed pineapple; drained</item></ing>
      <ing>
        <amt>
          <qty>2</qty>
          <unit/></amt>
        <item>Boxes (large) frozen strawberries; drained</item></ing>
      <ing>
        <amt>
          <qty>1</qty>
          <unit>container</unit></amt>
        <item>(large) Cool Whip</item></ing>
      <ing>
        <amt>
          <qty>1</qty>
          <unit>cup</unit></amt>
        <item>Chopped nuts</item></ing></ingredients>
    <directions>
      <step>  Combine graham cracker crumbs with melted butter; pat into bottom of a
  9x13-inch pan. Bake at 350 for 8-9 minutes. Cream together butter, powdered
  sugar, vanilla &amp; eggs. Spread over graham cracker mixture. Spread drained
  pineapple on bananas, then the strawberries, then the Cool Whip. Sprinkle
  with chopped nuts. Cover with plastic wrap. Chill for 6 hours before
  serving. Serves 15. Variation: Use vanilla wafer crumbs for the crust; use
  2 egg whites instead of 2 whole eggs; delete frozen strawberries. MRS
  JOANNE HUNT.
  
  MRS M.D. (MARY LOU) STARR
  
  From the &lt;The Bliss of Cooking Returns&gt;, Fort Bliss Officers Wives Club,
  Ft. Bliss, TX.  Downloaded from Glen's MM Recipe Archive,
  http://www.erols.com/hosey.
 
</step></directions></recipe></recipeml>
